boolean_switch/__init__.py
boolean_switch/admin.py
boolean_switch/models.py
boolean_switch/tests.py
boolean_switch/urls.py
boolean_switch/views.py
boolean_switch/static/boolean_switch/boolean_switch.js
django_boolean_switch-0.2.9.dist-info/LICENSE
django_boolean_switch-0.2.9.dist-info/METADATA
django_boolean_switch-0.2.9.dist-info/WHEEL
django_boolean_switch-0.2.9.dist-info/top_level.txt
django_boolean_switch-0.2.9.dist-info/RECORD
