Metadata-Version: 2.1
Name: django-boolean-switch
Version: 0.2.9
Summary: Django app to switch boolean fields from list view
Home-page: https://github.com/makeev/django-boolean-switch
Author: Mikhail Makeev
Author-email: mihail.makeev@gmail.com
License: UNKNOWN
Platform: UNKNOWN
Classifier: Environment :: Web Environment
Classifier: Framework :: Django
Classifier: Intended Audience :: Developers
Classifier: Operating System :: OS Independent
Classifier: Programming Language :: Python
